README.md
setup.cfg
setup.py
trs
src/__init__.py
src/clidriver.py
src/terraform_install.py
src/terraform_remote_state.py
trs.egg-info/PKG-INFO
trs.egg-info/SOURCES.txt
trs.egg-info/dependency_links.txt
trs.egg-info/requires.txt
trs.egg-info/top_level.txt
trs.egg-info/zip-safe