Metadata-Version: 1.1
Name: trs
Version: 1.0.6
Summary: 
